estimator_pkg_terry2124/.DS_Store
estimator_pkg_terry2124/Estimator.py
estimator_pkg_terry2124/__init__.py
estimator_pkg_terry2124-1.0.0.dist-info/METADATA
estimator_pkg_terry2124-1.0.0.dist-info/WHEEL
estimator_pkg_terry2124-1.0.0.dist-info/licenses/LICENSE
estimator_pkg_terry2124-1.0.0.dist-info/RECORD
