Metadata-Version: 2.1
Name: Estimator_pkg_Terry2124
Version: 1.0.0
Summary: Construction Estimator
Project-URL: Homepage, https://ngurunwild.ca
Project-URL: Bug Tracker, https://ngurunwild.ca
Author-email: Terry Boulanger <terry2124@me.com>
License: Copyright (c) 2018 The Python Packaging Authority
Classifier: License :: OSI Approved :: MIT License
Classifier: Operating System :: OS Independent
Classifier: Programming Language :: Python :: 3
Requires-Python: >=3.10
